rateExtrapolation/__init__.py
rateExtrapolation/k_folds_data_splitter.py
rateExtrapolation/parameter_estimation_fitness_evaluator.py
rateExtrapolation/rate_extrapolation.py
rateExtrapolation/sbstoat_model_fitting_to_folds.py
rateExtrapolation-1.0.1.dist-info/LICENSE
rateExtrapolation-1.0.1.dist-info/METADATA
rateExtrapolation-1.0.1.dist-info/WHEEL
rateExtrapolation-1.0.1.dist-info/top_level.txt
rateExtrapolation-1.0.1.dist-info/RECORD
